clipsai/__init__.py
clipsai/clip/__init__.py
clipsai/clip/clip.py
clipsai/clip/clipfinder.py
clipsai/clip/exceptions.py
clipsai/clip/text_embedder.py
clipsai/clip/texttiler.py
clipsai/diarize/__init__.py
clipsai/diarize/exceptions.py
clipsai/diarize/pyannote.py
clipsai/filesys/__init__.py
clipsai/filesys/dir.py
clipsai/filesys/exceptions.py
clipsai/filesys/file.py
clipsai/filesys/json_file.py
clipsai/filesys/manager.py
clipsai/filesys/object.py
clipsai/media/__init__.py
clipsai/media/audio_file.py
clipsai/media/audiovideo_file.py
clipsai/media/editor.py
clipsai/media/exceptions.py
clipsai/media/image_file.py
clipsai/media/media_file.py
clipsai/media/temporal_media_file.py
clipsai/media/video_file.py
clipsai/resize/__init__.py
clipsai/resize/crops.py
clipsai/resize/exceptions.py
clipsai/resize/img_proc.py
clipsai/resize/rect.py
clipsai/resize/resize.py
clipsai/resize/resizer.py
clipsai/resize/segment.py
clipsai/resize/vid_proc.py
clipsai/transcribe/__init__.py
clipsai/transcribe/exceptions.py
clipsai/transcribe/transcriber.py
clipsai/transcribe/transcription.py
clipsai/transcribe/transcription_element.py
clipsai/utils/__init__.py
clipsai/utils/config_manager.py
clipsai/utils/conversions.py
clipsai/utils/exception_handler.py
clipsai/utils/exceptions.py
clipsai/utils/pytorch.py
clipsai/utils/type_checker.py
clipsai/utils/utils.py
clipsai-0.2.1.dist-info/LICENSE
clipsai-0.2.1.dist-info/METADATA
clipsai-0.2.1.dist-info/WHEEL
clipsai-0.2.1.dist-info/top_level.txt
clipsai-0.2.1.dist-info/RECORD
