Metadata-Version: 2.1
Name: clipsai
Version: 0.2.1
Summary: Clips AI is an open-source Python library that automatically converts long videos into clips
Home-page: https://clipsai.com/
Author: Benjamin Smidt, Johann Ramirez, Armel Talla
Author-email: support@clipsai.com
License: MIT
Project-URL: Documentation, https://docs.clipsai.com/
Project-URL: Homepage, https://clipsai.com/
Project-URL: Repository, https://github.com/ClipsAI/clipsai
Project-URL: Issues, https://github.com/ClipsAI/clipsai/issues
Classifier: Programming Language :: Python :: 3
Classifier: License :: OSI Approved :: MIT License
Classifier: Operating System :: OS Independent
Requires-Python: >=3.9
License-File: LICENSE
Requires-Dist: av
Requires-Dist: facenet-pytorch
Requires-Dist: matplotlib
Requires-Dist: mediapipe
Requires-Dist: nltk
Requires-Dist: numpy
Requires-Dist: opencv-python
Requires-Dist: pandas
Requires-Dist: psutil
Requires-Dist: pyannote.audio
Requires-Dist: pyannote.core
Requires-Dist: pynvml
Requires-Dist: pytest
Requires-Dist: python-magic
Requires-Dist: scenedetect
Requires-Dist: scikit-learn
Requires-Dist: sentence-transformers
Requires-Dist: scipy
Requires-Dist: torch
Provides-Extra: dev
Requires-Dist: black; extra == "dev"
Requires-Dist: black[jupyter]; extra == "dev"
Requires-Dist: build; extra == "dev"
Requires-Dist: flake8; extra == "dev"
Requires-Dist: ipykernel; extra == "dev"
Requires-Dist: pytest; extra == "dev"
Requires-Dist: twine; extra == "dev"
